{
  "fontSize": "12px",
  "dayNumberFontSize": "15px",
  "navButtonHeight": "28px",
  "headerRowBold": false,
  "pwColumnBold": false,
  "pwColumnSeparatorColor": "rgba(173, 216, 230, 0.4)",
  "pwColumnFontColorLight": "rgba(70, 130, 180, 0.80)",
  "pwColumnFontColorDark": "rgba(224, 255, 255, 0.85)",
  "weekNumberFontColorLight": "rgba(100, 149, 237, 0.70)",
  "weekNumberFontColorDark": "rgba(224, 255, 255, 0.85)",
  "dayHeaderFontColorLight": "rgba(70, 130, 180, 0.85)",
  "dayHeaderFontColorDark": "rgba(221, 255, 255, 1.00)",
  "dayCellFontColorLight": "rgba(32, 178, 170, 1)",
  "dayCellFontColorDark": "rgba(224, 255, 255, 1.00)",
  "otherMonthFontColorLight": "rgba(210, 180, 140, 0.60)",
  "otherMonthFontColorDark": "rgba(189, 183, 107, 0.60)",
  "highlightTodayDayHeader": true,
  "highlightTodayPWLabel": true,
  "todayHighlightSize": "2.8em",
  "currentHighlightLabelColorLight": "rgba(255, 80, 80, 1.00)",
  "currentHighlightLabelColorDark": "rgba(255, 80, 80, 1.00)",
  "monthColorLight": "rgba(255, 165, 0, 1)",
  "monthColorDark": "rgba(0, 206, 209, 1.00)",
  "yearColorLight": "rgba(0, 98, 255, 1.00)",
  "yearColorDark": "rgba(255, 235, 102, 1.00)",
  "mainMonthYearTitleFontSize": "22px",
  "mainMonthTitleBold": true,
  "mainYearTitleBold": false,
  "tabTitleFontSize": "15px",
  "tabTitleBold": false,
  "selectedTabColor": "rgba(32, 178, 170, 1.00)",
  "todayHighlightColorLight": "rgba(255, 215, 0, 0.80)",
  "todayHighlightColorDark": "rgba(64, 224, 208, 0.70)",
  "notesHoverColor": "rgba(240, 255, 255, 0.30)",
  "dailyNoteDotColor": "rgba(255, 215, 0, 1.00)",
  "noteCreatedColor": "rgba(60, 179, 113, 0.80)",
  "noteModifiedColor": "rgba(255, 140, 0, 0.80)",
  "rowHighlightColorLight": "rgba(176, 224, 230, 0.15)",
  "rowHighlightColorDark": "rgba(0, 128, 128, 0.70)",
  "weekendShadeColorLight": "rgba(176, 224, 230, 0.15)",
  "weekendShadeColorDark": "rgba(95, 158, 160, 0.4)",
  "dateCellHoverColorLight": "rgba(255, 239, 213, 0.75)",
  "dateCellHoverColorDark": "rgba(32, 178, 170, 1)",
  "assetDotColor": "rgba(255, 69, 0, 1.00)",
  "calendarEventDotColor": "rgba(70, 130, 180, 1)",
  "todayHighlightStyle": "cell",
  "todayCircleColorLight": "rgba(255, 215, 0, 0.80)",
  "todayCircleColorDark": "rgba(0, 206, 209, 1.00)",
  "weeklyNoteDotColor": "rgba(32, 178, 170, 1)",
  "scratchFontSize": "14px",
  "scratchBold": false,
  "scratchFontFamily": "",
  "scratchpadHighlightColor": "rgba(255, 239, 213, 0.4)",
  "notesFontSize": "14px",
  "notesBold": false,
  "notesLineHeight": 22,
  "showNoteStatusDots": true,
  "otherNotePopupFontSize": "14px",
  "calendarDotSize": 4,
  "taskIndicatorStyle": "heatmap",
  "taskDotColor": "rgba(200, 100, 200, 1.00)",
  "taskBadgeFontSize": "11px",
  "taskBadgeColor": "rgba(255, 215, 0, 0.70)",
  "taskBadgeFontColor": "rgba(0, 0, 0, 1.00)",
  "taskHeatmapStartColor": "rgba(135, 206, 235, 0.30)",
  "taskHeatmapMidColor": "rgba(60, 179, 113, 0.45)",
  "taskHeatmapEndColor": "rgba(255, 140, 0, 0.60)",
  "taskHeadingFontSize": "13px",
  "taskTextFontSize": "14px",
  "taskGroupColorOverdue": "rgba(255, 69, 0, 0.20)",
  "taskGroupColorToday": "rgba(255, 165, 0, 0.25)",
  "taskGroupColorTomorrow": "rgba(60, 179, 113, 0.18)",
  "taskGroupColorNext7Days": "rgba(70, 130, 180, 0.18)",
  "taskGroupColorFuture": "rgba(210, 180, 140, 0.15)",
  "taskGroupColorNoDate": "rgba(255, 255, 224, 0.15)",
  "taskGroupColorTag": "rgba(32, 178, 170, 0.18)",
  "__exportType": "theme"
}